{
  "white": 113513,
  "draws": 13172,
  "black": 99802,
  "moves": [
    {
      "uci": "g8f6",
      "san": "Nf6",
      "white": 28094,
      "black": 25246,
      "draws": 3349
    },
    {
      "uci": "e7e5",
      "san": "e5",
      "white": 25065,
      "black": 21714,
      "draws": 2629
    },
    {
      "uci": "c7c5",
      "san": "c5",
      "white": 14123,
      "black": 12096,
      "draws": 1717
    },
    {
      "uci": "e7e6",
      "san": "e6",
      "white": 13621,
      "black": 12312,
      "draws": 1735
    },
    {
      "uci": "c7c6",
      "san": "c6",
      "white": 9367,
      "black": 8754,
      "draws": 1229
    },
    {
      "uci": "g7g6",
      "san": "g6",
      "white": 6144,
      "black": 5318,
      "draws": 722
    },
    {
      "uci": "d7d5",
      "san": "d5",
      "white": 5478,
      "black": 4404,
      "draws": 560
    },
    {
      "uci": "d7d6",
      "san": "d6",
      "white": 4213,
      "black": 3658,
      "draws": 477
    },
    {
      "uci": "f7f5",
      "san": "f5",
      "white": 2798,
      "black": 2379,
      "draws": 293
    },
    {
      "uci": "b7b6",
      "san": "b6",
      "white": 2233,
      "black": 1928,
      "draws": 243
    },
    {
      "uci": "b8c6",
      "san": "Nc6",
      "white": 1233,
      "black": 1097,
      "draws": 106
    },
    {
      "uci": "b7b5",
      "san": "b5",
      "white": 412,
      "black": 325,
      "draws": 37
    }
  ]
}