{
  "white": 10452,
  "draws": 1185,
  "black": 9047,
  "moves": [
    {
      "uci": "f6e4",
      "san": "Ne4",
      "white": 2929,
      "black": 2635,
      "draws": 284
    },
    {
      "uci": "e7e6",
      "san": "e6",
      "white": 2714,
      "black": 2310,
      "draws": 360
    },
    {
      "uci": "d7d5",
      "san": "d5",
      "white": 1514,
      "black": 1331,
      "draws": 217
    },
    {
      "uci": "g7g6",
      "san": "g6",
      "white": 1433,
      "black": 1074,
      "draws": 141
    },
    {
      "uci": "c7c5",
      "san": "c5",
      "white": 808,
      "black": 876,
      "draws": 90
    },
    {
      "uci": "d7d6",
      "san": "d6",
      "white": 359,
      "black": 279,
      "draws": 32
    },
    {
      "uci": "h7h6",
      "san": "h6",
      "white": 343,
      "black": 232,
      "draws": 35
    },
    {
      "uci": "c7c6",
      "san": "c6",
      "white": 218,
      "black": 218,
      "draws": 19
    },
    {
      "uci": "b7b6",
      "san": "b6",
      "white": 79,
      "black": 64,
      "draws": 5
    },
    {
      "uci": "b8c6",
      "san": "Nc6",
      "white": 12,
      "black": 11,
      "draws": 1
    },
    {
      "uci": "f6d5",
      "san": "Nd5",
      "white": 13,
      "black": 8,
      "draws": 1
    },
    {
      "uci": "f6g8",
      "san": "Ng8",
      "white": 9,
      "black": 3,
      "draws": 0
    }
  ]
}