{
  "white": 94518,
  "draws": 10572,
  "black": 90267,
  "moves": [
    {
      "uci": "e4d5",
      "san": "exd5",
      "white": 74101,
      "black": 71223,
      "draws": 8552
    },
    {
      "uci": "e4e5",
      "san": "e5",
      "white": 6561,
      "black": 6075,
      "draws": 620
    },
    {
      "uci": "b1c3",
      "san": "Nc3",
      "white": 5543,
      "black": 4733,
      "draws": 528
    },
    {
      "uci": "g1f3",
      "san": "Nf3",
      "white": 4269,
      "black": 4459,
      "draws": 480
    },
    {
      "uci": "d2d4",
      "san": "d4",
      "white": 2422,
      "black": 2255,
      "draws": 206
    },
    {
      "uci": "d2d3",
      "san": "d3",
      "white": 939,
      "black": 733,
      "draws": 120
    },
    {
      "uci": "f2f4",
      "san": "f4",
      "white": 183,
      "black": 225,
      "draws": 15
    },
    {
      "uci": "f2f3",
      "san": "f3",
      "white": 161,
      "black": 138,
      "draws": 13
    },
    {
      "uci": "b2b3",
      "san": "b3",
      "white": 86,
      "black": 91,
      "draws": 9
    },
    {
      "uci": "a2a3",
      "san": "a3",
      "white": 60,
      "black": 61,
      "draws": 4
    },
    {
      "uci": "f1c4",
      "san": "Bc4",
      "white": 23,
      "black": 65,
      "draws": 1
    },
    {
      "uci": "d1f3",
      "san": "Qf3",
      "white": 33,
      "black": 39,
      "draws": 9
    }
  ]
}