{
  "white": 140425,
  "draws": 17189,
  "black": 135163,
  "moves": [
    {
      "uci": "d2d4",
      "san": "d4",
      "white": 84780,
      "black": 78976,
      "draws": 10208
    },
    {
      "uci": "g1f3",
      "san": "Nf3",
      "white": 25454,
      "black": 26298,
      "draws": 3367
    },
    {
      "uci": "b1c3",
      "san": "Nc3",
      "white": 11379,
      "black": 11349,
      "draws": 1361
    },
    {
      "uci": "c2c4",
      "san": "c4",
      "white": 4893,
      "black": 4291,
      "draws": 601
    },
    {
      "uci": "f2f4",
      "san": "f4",
      "white": 4248,
      "black": 4551,
      "draws": 459
    },
    {
      "uci": "d2d3",
      "san": "d3",
      "white": 3875,
      "black": 3458,
      "draws": 459
    },
    {
      "uci": "f1c4",
      "san": "Bc4",
      "white": 2314,
      "black": 2720,
      "draws": 311
    },
    {
      "uci": "g1e2",
      "san": "Ne2",
      "white": 919,
      "black": 837,
      "draws": 95
    },
    {
      "uci": "e4e5",
      "san": "e5",
      "white": 568,
      "black": 582,
      "draws": 70
    },
    {
      "uci": "b2b3",
      "san": "b3",
      "white": 599,
      "black": 551,
      "draws": 61
    },
    {
      "uci": "c2c3",
      "san": "c3",
      "white": 490,
      "black": 544,
      "draws": 65
    },
    {
      "uci": "g2g3",
      "san": "g3",
      "white": 391,
      "black": 431,
      "draws": 70
    }
  ]
}