{
  "white": 360342,
  "draws": 39238,
  "black": 347051,
  "moves": [
    {
      "uci": "g1f3",
      "san": "Nf3",
      "white": 206305,
      "black": 199678,
      "draws": 23185
    },
    {
      "uci": "b1c3",
      "san": "Nc3",
      "white": 44052,
      "black": 39924,
      "draws": 4421
    },
    {
      "uci": "d2d4",
      "san": "d4",
      "white": 29587,
      "black": 28220,
      "draws": 3006
    },
    {
      "uci": "c2c3",
      "san": "c3",
      "white": 26721,
      "black": 24230,
      "draws": 3094
    },
    {
      "uci": "f2f4",
      "san": "f4",
      "white": 14178,
      "black": 15264,
      "draws": 1464
    },
    {
      "uci": "f1c4",
      "san": "Bc4",
      "white": 11750,
      "black": 12711,
      "draws": 1166
    },
    {
      "uci": "b2b4",
      "san": "b4",
      "white": 6146,
      "black": 5908,
      "draws": 533
    },
    {
      "uci": "d2d3",
      "san": "d3",
      "white": 4845,
      "black": 4966,
      "draws": 594
    },
    {
      "uci": "a2a3",
      "san": "a3",
      "white": 4356,
      "black": 3988,
      "draws": 440
    },
    {
      "uci": "c2c4",
      "san": "c4",
      "white": 4124,
      "black": 3884,
      "draws": 481
    },
    {
      "uci": "g2g3",
      "san": "g3",
      "white": 2459,
      "black": 2260,
      "draws": 265
    },
    {
      "uci": "b2b3",
      "san": "b3",
      "white": 2223,
      "black": 2217,
      "draws": 212
    }
  ]
}