{
  "white": 24193,
  "draws": 2022,
  "black": 24068,
  "moves": [
    {
      "uci": "e5f4",
      "san": "exf4",
      "white": 10041,
      "black": 9843,
      "draws": 807
    },
    {
      "uci": "d7d5",
      "san": "d5",
      "white": 4885,
      "black": 5433,
      "draws": 464
    },
    {
      "uci": "b8c6",
      "san": "Nc6",
      "white": 4635,
      "black": 4661,
      "draws": 367
    },
    {
      "uci": "d7d6",
      "san": "d6",
      "white": 2431,
      "black": 1929,
      "draws": 198
    },
    {
      "uci": "f8c5",
      "san": "Bc5",
      "white": 1090,
      "black": 1227,
      "draws": 94
    },
    {
      "uci": "g8f6",
      "san": "Nf6",
      "white": 613,
      "black": 557,
      "draws": 59
    },
    {
      "uci": "d8h4",
      "san": "Qh4+",
      "white": 141,
      "black": 117,
      "draws": 11
    },
    {
      "uci": "f7f5",
      "san": "f5",
      "white": 125,
      "black": 129,
      "draws": 8
    },
    {
      "uci": "c7c6",
      "san": "c6",
      "white": 57,
      "black": 58,
      "draws": 4
    },
    {
      "uci": "d8f6",
      "san": "Qf6",
      "white": 59,
      "black": 43,
      "draws": 2
    },
    {
      "uci": "f7f6",
      "san": "f6",
      "white": 45,
      "black": 27,
      "draws": 1
    },
    {
      "uci": "d8e7",
      "san": "Qe7",
      "white": 15,
      "black": 10,
      "draws": 0
    }
  ]
}