{
  "white": 18683,
  "draws": 1844,
  "black": 16166,
  "moves": [
    {
      "uci": "d2d4",
      "san": "d4",
      "white": 8896,
      "black": 7528,
      "draws": 888
    },
    {
      "uci": "f1c4",
      "san": "Bc4",
      "white": 7108,
      "black": 6200,
      "draws": 672
    },
    {
      "uci": "b1c3",
      "san": "Nc3",
      "white": 1143,
      "black": 959,
      "draws": 119
    },
    {
      "uci": "c2c3",
      "san": "c3",
      "white": 677,
      "black": 630,
      "draws": 76
    },
    {
      "uci": "h2h3",
      "san": "h3",
      "white": 380,
      "black": 370,
      "draws": 34
    },
    {
      "uci": "d2d3",
      "san": "d3",
      "white": 149,
      "black": 151,
      "draws": 11
    },
    {
      "uci": "f1b5",
      "san": "Bb5+",
      "white": 138,
      "black": 121,
      "draws": 13
    },
    {
      "uci": "f1e2",
      "san": "Be2",
      "white": 54,
      "black": 68,
      "draws": 11
    },
    {
      "uci": "c2c4",
      "san": "c4",
      "white": 48,
      "black": 43,
      "draws": 9
    },
    {
      "uci": "g2g3",
      "san": "g3",
      "white": 41,
      "black": 35,
      "draws": 6
    },
    {
      "uci": "b2b3",
      "san": "b3",
      "white": 24,
      "black": 29,
      "draws": 0
    },
    {
      "uci": "f1d3",
      "san": "Bd3",
      "white": 16,
      "black": 15,
      "draws": 1
    }
  ]
}